cmdscrypt.py
cmdscrypt-2.0.dist-info/METADATA
cmdscrypt-2.0.dist-info/WHEEL
cmdscrypt-2.0.dist-info/entry_points.txt
cmdscrypt-2.0.dist-info/top_level.txt
cmdscrypt-2.0.dist-info/RECORD
