Metadata-Version: 2.1
Name: cmdscrypt
Version: 2.0
Summary: A simple CLI app for generating Scrypt keys
Home-page: https://github.com/NotStatilko/cmdscrypt
Download-URL: https://github.com/NotStatilko/cmdscrypt/archive/refs/tags/v2.0.tar.gz
Author-email: thenonproton@pm.me
License: MIT
Requires-Dist: click ==8.1.3
